guolei_py3_database/__init__.py
guolei_py3_database/duckdb.py
guolei_py3_database/pymysql.py
guolei_py3_database/sqlite3.py
guolei_py3_database/strictredis.py
guolei_py3_database-0.0.23.dist-info/LICENSE
guolei_py3_database-0.0.23.dist-info/METADATA
guolei_py3_database-0.0.23.dist-info/WHEEL
guolei_py3_database-0.0.23.dist-info/top_level.txt
guolei_py3_database-0.0.23.dist-info/RECORD
