Metadata-Version: 2.1
Name: guolei-py3-database
Version: 0.0.23
Summary: guolei python3 database library
Home-page: https://github.com/guolei19850528/guolei_py3_database
Author: guolei
Author-email: 174000902@qq.com
License: MIT
Requires-Python: >=3.0
License-File: LICENSE
Requires-Dist: PyMySQL
Requires-Dist: redis
Requires-Dist: duckdb
Requires-Dist: diskcache
Requires-Dist: addict
Requires-Dist: retrying
Requires-Dist: pydantic
